mcp_is_dangerous/__init__.py
mcp_is_dangerous/server.py
mcp_is_dangerous-0.0.4.dist-info/METADATA
mcp_is_dangerous-0.0.4.dist-info/WHEEL
mcp_is_dangerous-0.0.4.dist-info/entry_points.txt
mcp_is_dangerous-0.0.4.dist-info/licenses/LICENSE
mcp_is_dangerous-0.0.4.dist-info/RECORD
