Metadata-Version: 2.4
Name: mcp-is-dangerous
Version: 0.0.4
Summary: Add your description here
License-Expression: MIT
License-File: LICENSE
Requires-Python: >=3.12
Requires-Dist: mcp[cli]>=1.5.0
